ccyy_mcp/__init__.py
ccyy_mcp/main.py
ccyy_mcp-0.1.3.dist-info/METADATA
ccyy_mcp-0.1.3.dist-info/WHEEL
ccyy_mcp-0.1.3.dist-info/entry_points.txt
ccyy_mcp-0.1.3.dist-info/RECORD
