Metadata-Version: 2.4
Name: ccyy-mcp
Version: 0.1.3
Summary: Add your description here
Requires-Dist: mcp[cli]>=1.12.0
